{
  "fontFamily": {
    "$value": "{typography.tokens.fontFamily.primary}",
    "$type": "fontFamily",
    "$unit": ""
  },
  "fontSize": {
    "$value": 32,
    "$type": "number",
    "$unit": "px"
  },
  "fontStyle": {
    "$value": "normal",
    "$type": "fontStyle",
    "$unit": ""
  },
  "fontWeight": {
    "$value": "{typography.tokens.fontWeight.bold}",
    "$type": "fontWeight",
    "$unit": ""
  },
  "lineHeight": {
    "$value": 40,
    "$type": "number",
    "$unit": "px"
  },
  "letterSpacing": {
    "$value": -0.3,
    "$type": "letterSpacing",
    "$unit": "px"
  },
  "marginBottom": {
    "$value": "{tokens.spacing.xs}",
    "$type": "number",
    "$unit": "px"
  }
}
